smlib/__init__.py
smlib/_version.py
smlib/fsm.py
smlib/fsmTemplate.py
smlib/fsmWatchdog.py
smlib/io.py
smlib/loader.py
smlib/logger.py
smlib/timer.py
pysmlib-3.4.2.dist-info/LICENSE.txt
pysmlib-3.4.2.dist-info/METADATA
pysmlib-3.4.2.dist-info/WHEEL
pysmlib-3.4.2.dist-info/top_level.txt
pysmlib-3.4.2.dist-info/RECORD
