Metadata-Version: 2.1
Name: pysmlib
Version: 3.4.2
Summary: Python Finite State Machines for EPICS
Home-page: https://darcato.github.io/pysmlib/docs/html/
Download-URL: https://github.com/darcato/pysmlib
Author: Damiano Bortolato - Davide Marcato
Author-email: davide.marcato@lnl.infn.it
License: GPLv3
Requires-Python: >=3.6
License-File: LICENSE.txt
Requires-Dist: pyepics
